tox_poetry_dev_dependencies/__init__.py
tox_poetry_dev_dependencies/_hooks.py
tox_poetry_dev_dependencies-0.0.9.dist-info/LICENSE.txt
tox_poetry_dev_dependencies-0.0.9.dist-info/METADATA
tox_poetry_dev_dependencies-0.0.9.dist-info/WHEEL
tox_poetry_dev_dependencies-0.0.9.dist-info/entry_points.txt
tox_poetry_dev_dependencies-0.0.9.dist-info/top_level.txt
tox_poetry_dev_dependencies-0.0.9.dist-info/RECORD
