Metadata-Version: 2.1
Name: tox-poetry-dev-dependencies
Version: 0.0.9
Summary: Tox plugin to help working with Poetry-based projects
Home-page: https://pypi.org/project/tox-poetry-dev-dependencies/
Author: sinoroc
Author-email: sinoroc.code+python@gmail.com
License: Apache-2.0
Project-URL: GitHub, https://github.com/sinoroc/tox-poetry-dev-dependencies
Project-URL: GitLab, https://gitlab.com/sinoroc/tox-poetry-dev-dependencies
Platform: UNKNOWN
Classifier: Development Status :: 2 - Pre-Alpha
Classifier: Framework :: tox
Classifier: Programming Language :: Python :: 3 :: Only
Classifier: Programming Language :: Python :: 3.5
Classifier: Programming Language :: Python :: 3.6
Classifier: Programming Language :: Python :: 3.7
Classifier: Programming Language :: Python :: 3.8
Classifier: Programming Language :: Python :: 3.9
Classifier: Topic :: Software Development :: Testing
Classifier: Typing :: Typed
Requires-Python: ~=3.5
Requires-Dist: poetry-core (~=1.0)
Requires-Dist: tomlkit
Requires-Dist: tox
Provides-Extra: dev_package
Requires-Dist: twine ; extra == 'dev_package'
Requires-Dist: wheel ; extra == 'dev_package'
Provides-Extra: dev_test
Requires-Dist: mypy ; extra == 'dev_test'
Requires-Dist: pycodestyle ; extra == 'dev_test'
Requires-Dist: pydocstyle ; extra == 'dev_test'
Requires-Dist: pylint ; extra == 'dev_test'
Requires-Dist: pytest ; extra == 'dev_test'
Requires-Dist: pytest-mypy ; extra == 'dev_test'
Requires-Dist: pytest-pycodestyle ; extra == 'dev_test'
Requires-Dist: pytest-pydocstyle ; extra == 'dev_test'
Requires-Dist: pytest-pylint ; extra == 'dev_test'
Requires-Dist: pytest-yapf3 ; extra == 'dev_test'
Requires-Dist: yapf ; extra == 'dev_test'
